{
  "app": "CLI Studio",
  "actors": 10,
  "operations": 100,
  "visualScenario": true,
  "realRpcTouched": true,
  "realBroadcast": false,
  "domainOperationReal": true,
  "networkSettlementReal": false,
  "fallbackUsed": true,
  "packagesExercised": [
    "@hardkas/cli",
    "@hardkas/core",
    "@hardkas/dev-server",
    "@hardkas/config",
    "@hardkas/plugin-rpc-backend"
  ],
  "publicApisExercised": [
    "buildHardkasProgram",
    "Command.parseAsync",
    "parseHardkasConfig"
  ],
  "errors": [],
  "expectedGuards": [
    "Missing required environment variables",
    "CLI exited with code 1",
    "Missing required environment variables",
    "CLI exited with code 1",
    "Missing required environment variables",
    "CLI exited with code 1",
    "Missing required environment variables",
    "CLI exited with code 1",
    "Missing required environment variables",
    "CLI exited with code 1",
    "Missing required environment variables",
    "CLI exited with code 1",
    "Missing required environment variables",
    "CLI exited with code 1",
    "Missing required environment variables",
    "CLI exited with code 1",
    "Missing required environment variables",
    "CLI exited with code 1",
    "Missing required environment variables",
    "CLI exited with code 1",
    "Missing required environment variables",
    "CLI exited with code 1",
    "Missing required environment variables",
    "CLI exited with code 1",
    "Missing required environment variables",
    "CLI exited with code 1",
    "Missing required environment variables",
    "CLI exited with code 1",
    "Missing required environment variables",
    "CLI exited with code 1",
    "Missing required environment variables",
    "CLI exited with code 1",
    "Missing required environment variables",
    "CLI exited with code 1",
    "Missing required environment variables",
    "CLI exited with code 1",
    "Missing required environment variables",
    "CLI exited with code 1",
    "Missing required environment variables",
    "CLI exited with code 1",
    "Missing required environment variables",
    "CLI exited with code 1",
    "Missing required environment variables",
    "CLI exited with code 1",
    "Missing required environment variables",
    "CLI exited with code 1",
    "Missing required environment variables",
    "CLI exited with code 1",
    "Missing required environment variables",
    "CLI exited with code 1"
  ],
  "unsupportedCapabilities": []
}